cardio_rl/__init__.py
cardio_rl/agent.py
cardio_rl/buffers/__init__.py
cardio_rl/buffers/base_buffer.py
cardio_rl/buffers/eff_buffer.py
cardio_rl/buffers/eff_mixed_buffer.py
cardio_rl/buffers/mixed_buffer.py
cardio_rl/buffers/prioritised_buffer.py
cardio_rl/buffers/tree_buffer.py
cardio_rl/evaluation.py
cardio_rl/gatherers/__init__.py
cardio_rl/gatherers/gatherer.py
cardio_rl/gatherers/vector.py
cardio_rl/loggers/__init__.py
cardio_rl/loggers/base_logger.py
cardio_rl/loggers/tb_logger.py
cardio_rl/loggers/wandb_logger.py
cardio_rl/runners/__init__.py
cardio_rl/runners/runner.py
cardio_rl/toy_env.py
cardio_rl/tree.py
cardio_rl/types.py
cardio_rl/wrappers/__init__.py
cardio_rl/wrappers/atari.py
cardio_rl/wrappers/envpool.py
cardio_rl/wrappers/gymnasium_atari.py
cardio_rl-0.1.2.dist-info/LICENSE
cardio_rl-0.1.2.dist-info/METADATA
cardio_rl-0.1.2.dist-info/WHEEL
cardio_rl-0.1.2.dist-info/RECORD
