Metadata-Version: 2.3
Name: cardio-rl
Version: 0.1.2
Summary: Cardio RL. In development...
License: Apache-2.0
Author: Manus McAuliffe
Author-email: mmcaulif@tcd.ie
Requires-Python: >=3.10,<3.12
Classifier: Development Status :: 3 - Alpha
Classifier: License :: OSI Approved :: Apache Software License
Classifier: Programming Language :: Python :: 3
Classifier: Programming Language :: Python :: 3.10
Classifier: Programming Language :: Python :: 3.11
Requires-Dist: gymnasium (>=0.28.0,<0.29.0)
Requires-Dist: jax (>=0.4.25,<0.4.30)
Requires-Dist: jaxlib (>=0.4.25,<0.4.30)
Requires-Dist: numpy (>=1.21.0,<2.0.0)
Requires-Dist: tqdm (>=4.66.5,<5.0.0)
Project-URL: Repository, https://github.com/mmcaulif/Cardio
